<?xml version="1.0" encoding="utf-8" standalone="yes"?>
<set xmlns:noNamespaceSchemaLocation="CardSet.xsd"
     name="The Forest Moon"
     id="15d68fb0-747d-4148-bcda-3d89b7f2cfe8"
     gameId="d5cf89e5-1984-4873-8ae0-f06eea411bb3"
     gameVersion="2.0.0.0"
     version="2.0.0.0">
	<cards>
		<card id="ff4fb461-8060-457a-9c16-000000001231" name="Matter Under Mind" size="ObjectiveSize">
			<property name="Cost" value="0" />
			<property name="Type" value="Objective" />
			<property name="Force" value="0" />
			<property name="Combat Icons" value="UD:0, BD:0, T:0, EE-UD:0, EE-BD:0, EE-T:0" />
			<property name="Traits" value="Tatooine" />
			<property name="Damage Capacity" value="4" />
			<property name="Resources" value="2" />
			<property name="Edge Priority" value="" />
			<property name="Text" value="" />
			<property name="Flavor" value="" />
			<property name="Side" value="Light" />
			<property name="Affiliation" value="Jedi" />
			<property name="Block" value="196" />
			<property name="Block Number" value="1" />
			<property name="Number" value="959" />
			<property name="Instructions" value="" />
			<property name="AutoScript" value="" />
			<property name="AutoAction" value="" />
		</card>
		<card id="ff4fb461-8060-457a-9c16-000000001232" name="Brainiac">
			<property name="Cost" value="2" />
			<property name="Type" value="Unit" />
			<property name="Force" value="2" />
			<property name="Combat Icons" value="UD:0, BD:0, T:1, EE-UD:0, EE-BD:0, EE-T:0" />
			<property name="Traits" value="Character-Force Sensitive-Unique" />
			<property name="Damage Capacity" value="2" />
			<property name="Resources" value="0" />
			<property name="Edge Priority" value="" />
			<property name="Text" value="Action: Until the end of the phase, increase or decrease a numeral on a target non-objective card in play by 1. (Limit once per turn.)" />
			<property name="Flavor" value="" />
			<property name="Side" value="Light" />
			<property name="Affiliation" value="Jedi" />
			<property name="Block" value="196" />
			<property name="Block Number" value="2" />
			<property name="Number" value="960" />
			<property name="Instructions" value="" />
			<property name="AutoScript" value="" />
			<property name="AutoAction" value="" />
		</card>
		<card id="ff4fb461-8060-457a-9c16-000000001233" name="Unhinged Astromech">
			<property name="Cost" value="1" />
			<property name="Type" value="Unit" />
			<property name="Force" value="1" />
			<property name="Combat Icons" value="UD:0, BD:0, T:0, EE-UD:0, EE-BD:1, EE-T:0" />
			<property name="Traits" value="Droid" />
			<property name="Damage Capacity" value="1" />
			<property name="Resources" value="0" />
			<property name="Edge Priority" value="" />
			<property name="Text" value="While you control 2 or more copies of Unhinged Astromech, this unit gains: &#34;Action: Sacrifice this unit to (choose 1): Deal 1 damage to a target unit, discard 1 card at random from an opponent&#39;s hand, or remove up to 3 damage from a target unit.&#34;" />
			<property name="Flavor" value="" />
			<property name="Side" value="Light" />
			<property name="Affiliation" value="Neutral" />
			<property name="Block" value="196" />
			<property name="Block Number" value="3" />
			<property name="Number" value="961" />
			<property name="Instructions" value="" />
			<property name="AutoScript" value="" />
			<property name="AutoAction" value="" />
		</card>
		<card id="ff4fb461-8060-457a-9c16-000000001234" name="Unhinged Astromech">
			<property name="Cost" value="1" />
			<property name="Type" value="Unit" />
			<property name="Force" value="1" />
			<property name="Combat Icons" value="UD:0, BD:0, T:0, EE-UD:0, EE-BD:1, EE-T:0" />
			<property name="Traits" value="Droid" />
			<property name="Damage Capacity" value="1" />
			<property name="Resources" value="0" />
			<property name="Edge Priority" value="" />
			<property name="Text" value="While you control 2 or more copies of Unhinged Astromech, this unit gains: &#34;Action: Sacrifice this unit to (choose 1): Deal 1 damage to a target unit, discard 1 card at random from an opponent&#39;s hand, or remove up to 3 damage from a target unit.&#34;" />
			<property name="Flavor" value="" />
			<property name="Side" value="Light" />
			<property name="Affiliation" value="Neutral" />
			<property name="Block" value="196" />
			<property name="Block Number" value="4" />
			<property name="Number" value="961" />
			<property name="Instructions" value="" />
			<property name="AutoScript" value="" />
			<property name="AutoAction" value="" />
		</card>
		<card id="ff4fb461-8060-457a-9c16-000000001235" name="Signal Scrambler">
			<property name="Cost" value="1" />
			<property name="Type" value="Enhancement" />
			<property name="Force" value="2" />
			<property name="Combat Icons" value="UD:0, BD:0, T:0, EE-UD:0, EE-BD:0, EE-T:0" />
			<property name="Traits" value="" />
			<property name="Damage Capacity" value="0" />
			<property name="Resources" value="0" />
			<property name="Edge Priority" value="" />
			<property name="Text" value="Enhance your play area.&#xD;&#xA;Units committed to the Force do not contribute their Force icons to the Force struggle, and each ready unit not committed to the Force does." />
			<property name="Flavor" value="" />
			<property name="Side" value="Light" />
			<property name="Affiliation" value="Jedi" />
			<property name="Block" value="196" />
			<property name="Block Number" value="5" />
			<property name="Number" value="962" />
			<property name="Instructions" value="" />
			<property name="AutoScript" value="" />
			<property name="AutoAction" value="" />
		</card>
		<card id="ff4fb461-8060-457a-9c16-000000001236" name="Outwit">
			<property name="Cost" value="0" />
			<property name="Type" value="Event" />
			<property name="Force" value="1" />
			<property name="Combat Icons" value="UD:0, BD:0, T:0, EE-UD:0, EE-BD:0, EE-T:0" />
			<property name="Traits" value="Endor" />
			<property name="Damage Capacity" value="0" />
			<property name="Resources" value="0" />
			<property name="Edge Priority" value="" />
			<property name="Text" value="Reaction: After edge stacks are revealed, resolve fate cards from highest priority to lowest priority (instead of from lowest to highest) for this edge battle. Then, draw 1 card." />
			<property name="Flavor" value="" />
			<property name="Side" value="Light" />
			<property name="Affiliation" value="Jedi" />
			<property name="Block" value="196" />
			<property name="Block Number" value="6" />
			<property name="Number" value="963" />
			<property name="Instructions" value="" />
			<property name="AutoScript" value="" />
			<property name="AutoAction" value="" />
		</card>
		<card id="ff4fb461-8060-457a-9c16-000000001237" name="Solidarity of Spirit" size="ObjectiveSize">
			<property name="Cost" value="0" />
			<property name="Type" value="Objective" />
			<property name="Force" value="0" />
			<property name="Combat Icons" value="UD:0, BD:0, T:0, EE-UD:0, EE-BD:0, EE-T:0" />
			<property name="Traits" value="Endor" />
			<property name="Damage Capacity" value="5" />
			<property name="Resources" value="1" />
			<property name="Edge Priority" value="" />
			<property name="Text" value="Rebel Alliance affiliation only.&#xD;&#xA;Reaction: After this objective enters play, put a [Rebel Alliance] unit into play from your hand. Then, your opponent may put an in-faction unit with equal or lower printed cost into play from his hand." />
			<property name="Flavor" value="" />
			<property name="Side" value="Light" />
			<property name="Affiliation" value="Rebel Alliance" />
			<property name="Block" value="197" />
			<property name="Block Number" value="1" />
			<property name="Number" value="964" />
			<property name="Instructions" value="" />
			<property name="AutoScript" value="" />
			<property name="AutoAction" value="" />
		</card>
		<card id="ff4fb461-8060-457a-9c16-000000001238" name="Home One">
			<property name="Cost" value="5" />
			<property name="Type" value="Unit" />
			<property name="Force" value="3" />
			<property name="Combat Icons" value="UD:2, BD:1, T:0, EE-UD:1, EE-BD:1, EE-T:0" />
			<property name="Traits" value="Vehicle-Capital Ship-Unique" />
			<property name="Damage Capacity" value="4" />
			<property name="Resources" value="0" />
			<property name="Edge Priority" value="" />
			<property name="Text" value="Elite.&#xD;&#xA;Reaction: After this unit resolves its blast damage icons, resolve those icons again against a different enemy objective. (Limit once per round.)" />
			<property name="Flavor" value="" />
			<property name="Side" value="Light" />
			<property name="Affiliation" value="Rebel Alliance" />
			<property name="Block" value="197" />
			<property name="Block Number" value="2" />
			<property name="Number" value="965" />
			<property name="Instructions" value="" />
			<property name="AutoScript" value="" />
			<property name="AutoAction" value="" />
		</card>
		<card id="ff4fb461-8060-457a-9c16-000000001239" name="MC80 Liberty-type Cruiser">
			<property name="Cost" value="3" />
			<property name="Type" value="Unit" />
			<property name="Force" value="1" />
			<property name="Combat Icons" value="UD:1, BD:0, T:0, EE-UD:1, EE-BD:1, EE-T:0" />
			<property name="Traits" value="Vehicle-Capital Ship" />
			<property name="Damage Capacity" value="3" />
			<property name="Resources" value="0" />
			<property name="Edge Priority" value="" />
			<property name="Text" value="Reaction: After this unit enters play, reduce the cost of the next Vehicle unit you play this turn by 1 (to a minimum of 1)." />
			<property name="Flavor" value="" />
			<property name="Side" value="Light" />
			<property name="Affiliation" value="Rebel Alliance" />
			<property name="Block" value="197" />
			<property name="Block Number" value="3" />
			<property name="Number" value="966" />
			<property name="Instructions" value="" />
			<property name="AutoScript" value="" />
			<property name="AutoAction" value="" />
		</card>
		<card id="ff4fb461-8060-457a-9c16-000000001240" name="MC80 Liberty-type Cruiser">
			<property name="Cost" value="3" />
			<property name="Type" value="Unit" />
			<property name="Force" value="1" />
			<property name="Combat Icons" value="UD:1, BD:0, T:0, EE-UD:1, EE-BD:1, EE-T:0" />
			<property name="Traits" value="Vehicle-Capital Ship" />
			<property name="Damage Capacity" value="3" />
			<property name="Resources" value="0" />
			<property name="Edge Priority" value="" />
			<property name="Text" value="Reaction: After this unit enters play, reduce the cost of the next Vehicle unit you play this turn by 1 (to a minimum of 1)." />
			<property name="Flavor" value="" />
			<property name="Side" value="Light" />
			<property name="Affiliation" value="Rebel Alliance" />
			<property name="Block" value="197" />
			<property name="Block Number" value="4" />
			<property name="Number" value="966" />
			<property name="Instructions" value="" />
			<property name="AutoScript" value="" />
			<property name="AutoAction" value="" />
		</card>
		<card id="ff4fb461-8060-457a-9c16-000000001241" name="Rebel Fleet Command">
			<property name="Cost" value="0" />
			<property name="Type" value="Enhancement" />
			<property name="Force" value="0" />
			<property name="Combat Icons" value="UD:0, BD:0, T:0, EE-UD:0, EE-BD:0, EE-T:0" />
			<property name="Traits" value="" />
			<property name="Damage Capacity" value="0" />
			<property name="Resources" value="1" />
			<property name="Edge Priority" value="" />
			<property name="Text" value="Enhance your play area.&#xD;&#xA;Limited.&#xD;&#xA;Resources generated by this enhancement can only be used to play [Rebel Alliance] cards with printed cost 3 or higher." />
			<property name="Flavor" value="" />
			<property name="Side" value="Light" />
			<property name="Affiliation" value="Rebel Alliance" />
			<property name="Block" value="197" />
			<property name="Block Number" value="5" />
			<property name="Number" value="967" />
			<property name="Instructions" value="" />
			<property name="AutoScript" value="" />
			<property name="AutoAction" value="" />
		</card>
		<card id="ff4fb461-8060-457a-9c16-000000001242" name="Battle of Endor">
			<property name="Cost" value="0" />
			<property name="Type" value="Fate" />
			<property name="Force" value="1" />
			<property name="Combat Icons" value="UD:0, BD:0, T:0, EE-UD:0, EE-BD:0, EE-T:0" />
			<property name="Traits" value="" />
			<property name="Damage Capacity" value="0" />
			<property name="Resources" value="0" />
			<property name="Edge Priority" value="9" />
			<property name="Text" value="For this edge battle, this card gains +1 Force icon (to a maximum of +3) for each Endor objective or enhancement in play." />
			<property name="Flavor" value="" />
			<property name="Side" value="Light" />
			<property name="Affiliation" value="Neutral" />
			<property name="Block" value="197" />
			<property name="Block Number" value="6" />
			<property name="Number" value="942" />
			<property name="Instructions" value="" />
			<property name="AutoScript" value="" />
			<property name="AutoAction" value="" />
		</card>
		<card id="ff4fb461-8060-457a-9c16-000000001243" name="Sowers of Dissension" size="ObjectiveSize">
			<property name="Cost" value="0" />
			<property name="Type" value="Objective" />
			<property name="Force" value="0" />
			<property name="Combat Icons" value="UD:0, BD:0, T:0, EE-UD:0, EE-BD:0, EE-T:0" />
			<property name="Traits" value="Cloud City" />
			<property name="Damage Capacity" value="5" />
			<property name="Resources" value="1" />
			<property name="Edge Priority" value="" />
			<property name="Text" value="Reaction: After this objective enters play, deal 1 damage to each out-of-faction objective each player controls." />
			<property name="Flavor" value="" />
			<property name="Side" value="Light" />
			<property name="Affiliation" value="Smugglers and Spies" />
			<property name="Block" value="198" />
			<property name="Block Number" value="1" />
			<property name="Number" value="968" />
			<property name="Instructions" value="" />
			<property name="AutoScript" value="" />
			<property name="AutoAction" value="" />
		</card>
		<card id="ff4fb461-8060-457a-9c16-000000001244" name="Lobot">
			<property name="Cost" value="3" />
			<property name="Type" value="Unit" />
			<property name="Force" value="2" />
			<property name="Combat Icons" value="UD:1, BD:1, T:0, EE-UD:0, EE-BD:0, EE-T:0" />
			<property name="Traits" value="Character-Cyborg-Unique" />
			<property name="Damage Capacity" value="3" />
			<property name="Resources" value="0" />
			<property name="Edge Priority" value="" />
			<property name="Text" value="Shielding.&#xD;&#xA;Each enemy out-of-faction objective requires 1 fewer damage to destroy." />
			<property name="Flavor" value="" />
			<property name="Side" value="Light" />
			<property name="Affiliation" value="Smugglers and Spies" />
			<property name="Block" value="198" />
			<property name="Block Number" value="2" />
			<property name="Number" value="969" />
			<property name="Instructions" value="" />
			<property name="AutoScript" value="" />
			<property name="AutoAction" value="" />
		</card>
		<card id="ff4fb461-8060-457a-9c16-000000001245" name="Duros Saboteur">
			<property name="Cost" value="2" />
			<property name="Type" value="Unit" />
			<property name="Force" value="1" />
			<property name="Combat Icons" value="UD:0, BD:1, T:0, EE-UD:0, EE-BD:1, EE-T:0" />
			<property name="Traits" value="Character" />
			<property name="Damage Capacity" value="2" />
			<property name="Resources" value="0" />
			<property name="Edge Priority" value="" />
			<property name="Text" value="Reaction: After this unit uses its blast damage to damage an enemy objective, deal damage equal to the damage taken to each other copy of that objective. (Limit once per turn.)" />
			<property name="Flavor" value="" />
			<property name="Side" value="Light" />
			<property name="Affiliation" value="Smugglers and Spies" />
			<property name="Block" value="198" />
			<property name="Block Number" value="3" />
			<property name="Number" value="970" />
			<property name="Instructions" value="" />
			<property name="AutoScript" value="" />
			<property name="AutoAction" value="" />
		</card>
		<card id="ff4fb461-8060-457a-9c16-000000001246" name="Duros Saboteur">
			<property name="Cost" value="2" />
			<property name="Type" value="Unit" />
			<property name="Force" value="1" />
			<property name="Combat Icons" value="UD:0, BD:1, T:0, EE-UD:0, EE-BD:1, EE-T:0" />
			<property name="Traits" value="Character" />
			<property name="Damage Capacity" value="2" />
			<property name="Resources" value="0" />
			<property name="Edge Priority" value="" />
			<property name="Text" value="Reaction: After this unit uses its blast damage to damage an enemy objective, deal damage equal to the damage taken to each other copy of that objective. (Limit once per turn.)" />
			<property name="Flavor" value="" />
			<property name="Side" value="Light" />
			<property name="Affiliation" value="Smugglers and Spies" />
			<property name="Block" value="198" />
			<property name="Block Number" value="4" />
			<property name="Number" value="970" />
			<property name="Instructions" value="" />
			<property name="AutoScript" value="" />
			<property name="AutoAction" value="" />
		</card>
		<card id="ff4fb461-8060-457a-9c16-000000001247" name="Paid Off">
			<property name="Cost" value="0" />
			<property name="Type" value="Enhancement" />
			<property name="Force" value="1" />
			<property name="Combat Icons" value="UD:0, BD:0, T:0, EE-UD:0, EE-BD:0, EE-T:0" />
			<property name="Traits" value="Condition" />
			<property name="Damage Capacity" value="0" />
			<property name="Resources" value="0" />
			<property name="Edge Priority" value="" />
			<property name="Text" value="Enhance an out-of-faction enemy unit.&#xD;&#xA;Enhanced unit loses 2 Force icons." />
			<property name="Flavor" value="" />
			<property name="Side" value="Light" />
			<property name="Affiliation" value="Neutral" />
			<property name="Block" value="198" />
			<property name="Block Number" value="5" />
			<property name="Number" value="971" />
			<property name="Instructions" value="" />
			<property name="AutoScript" value="" />
			<property name="AutoAction" value="" />
		</card>
		<card id="ff4fb461-8060-457a-9c16-000000001248" name="Hiding Among Friends">
			<property name="Cost" value="0" />
			<property name="Type" value="Event" />
			<property name="Force" value="2" />
			<property name="Combat Icons" value="UD:0, BD:0, T:0, EE-UD:0, EE-BD:0, EE-T:0" />
			<property name="Traits" value="Tactic" />
			<property name="Damage Capacity" value="0" />
			<property name="Resources" value="0" />
			<property name="Edge Priority" value="" />
			<property name="Text" value="Action: Place 1 shield on a target [Smugglers and Spies] Character unit. Then, draw 1 card." />
			<property name="Flavor" value="" />
			<property name="Side" value="Light" />
			<property name="Affiliation" value="Smugglers and Spies" />
			<property name="Block" value="198" />
			<property name="Block Number" value="6" />
			<property name="Number" value="972" />
			<property name="Instructions" value="" />
			<property name="AutoScript" value="" />
			<property name="AutoAction" value="" />
		</card>
		<card id="ff4fb461-8060-457a-9c16-000000001249" name="Dark Counsel" size="ObjectiveSize">
			<property name="Cost" value="0" />
			<property name="Type" value="Objective" />
			<property name="Force" value="0" />
			<property name="Combat Icons" value="UD:0, BD:0, T:0, EE-UD:0, EE-BD:0, EE-T:0" />
			<property name="Traits" value="Death Star-Endor" />
			<property name="Damage Capacity" value="5" />
			<property name="Resources" value="1" />
			<property name="Edge Priority" value="" />
			<property name="Text" value="Reaction: After a target damaged enemy unit is focused to strike, place 1 focus token on that unit. (Limit once per turn.)" />
			<property name="Flavor" value="" />
			<property name="Side" value="Dark" />
			<property name="Affiliation" value="Sith" />
			<property name="Block" value="199" />
			<property name="Block Number" value="1" />
			<property name="Number" value="973" />
			<property name="Instructions" value="" />
			<property name="AutoScript" value="" />
			<property name="AutoAction" value="" />
		</card>
		<card id="ff4fb461-8060-457a-9c16-000000001250" name="Janus Greejatus">
			<property name="Cost" value="4" />
			<property name="Type" value="Unit" />
			<property name="Force" value="3" />
			<property name="Combat Icons" value="UD:1, BD:1, T:0, EE-UD:0, EE-BD:0, EE-T:1" />
			<property name="Traits" value="Character-Force Sensitive-Unique" />
			<property name="Damage Capacity" value="3" />
			<property name="Resources" value="0" />
			<property name="Edge Priority" value="" />
			<property name="Text" value="Elite.&#xD;&#xA;Reaction: After this unit is focused to strike, deal 1 damage to each participating enemy unit." />
			<property name="Flavor" value="" />
			<property name="Side" value="Dark" />
			<property name="Affiliation" value="Sith" />
			<property name="Block" value="199" />
			<property name="Block Number" value="2" />
			<property name="Number" value="974" />
			<property name="Instructions" value="" />
			<property name="AutoScript" value="" />
			<property name="AutoAction" value="" />
		</card>
		<card id="ff4fb461-8060-457a-9c16-000000001251" name="Imperial Functionary">
			<property name="Cost" value="2" />
			<property name="Type" value="Unit" />
			<property name="Force" value="1" />
			<property name="Combat Icons" value="UD:1, BD:0, T:0, EE-UD:1, EE-BD:0, EE-T:0" />
			<property name="Traits" value="Character" />
			<property name="Damage Capacity" value="2" />
			<property name="Resources" value="0" />
			<property name="Edge Priority" value="" />
			<property name="Text" value="Each enemy unit loses all instances of protect.&#xD;&#xA;Damage cannot be removed from units by card effects." />
			<property name="Flavor" value="" />
			<property name="Side" value="Dark" />
			<property name="Affiliation" value="Neutral" />
			<property name="Block" value="199" />
			<property name="Block Number" value="3" />
			<property name="Number" value="975" />
			<property name="Instructions" value="" />
			<property name="AutoScript" value="" />
			<property name="AutoAction" value="" />
		</card>
		<card id="ff4fb461-8060-457a-9c16-000000001252" name="Sith Library">
			<property name="Cost" value="1" />
			<property name="Type" value="Enhancement" />
			<property name="Force" value="0" />
			<property name="Combat Icons" value="UD:0, BD:0, T:0, EE-UD:1, EE-BD:1, EE-T:0" />
			<property name="Traits" value="Coruscant-Location" />
			<property name="Damage Capacity" value="0" />
			<property name="Resources" value="1" />
			<property name="Edge Priority" value="" />
			<property name="Text" value="Enhance your play area.&#xD;&#xA;Limited. (You cannot play more than one limited card per turn.)" />
			<property name="Flavor" value="" />
			<property name="Side" value="Dark" />
			<property name="Affiliation" value="Neutral" />
			<property name="Block" value="199" />
			<property name="Block Number" value="4" />
			<property name="Number" value="072" />
			<property name="Instructions" value="" />
			<property name="AutoScript" value="" />
			<property name="AutoAction" value="" />
		</card>
		<card id="ff4fb461-8060-457a-9c16-000000001253" name="Administrative Detainment">
			<property name="Cost" value="1" />
			<property name="Type" value="Event" />
			<property name="Force" value="1" />
			<property name="Combat Icons" value="UD:0, BD:0, T:0, EE-UD:0, EE-BD:0, EE-T:0" />
			<property name="Traits" value="" />
			<property name="Damage Capacity" value="0" />
			<property name="Resources" value="0" />
			<property name="Edge Priority" value="" />
			<property name="Text" value="Action: Place 1 focus token on a target Character unit. If that unit is damaged, place 2 focus tokens on it instead." />
			<property name="Flavor" value="" />
			<property name="Side" value="Dark" />
			<property name="Affiliation" value="Sith" />
			<property name="Block" value="199" />
			<property name="Block Number" value="5" />
			<property name="Number" value="976" />
			<property name="Instructions" value="" />
			<property name="AutoScript" value="" />
			<property name="AutoAction" value="" />
		</card>
		<card id="ff4fb461-8060-457a-9c16-000000001254" name="Battle of Endor">
			<property name="Cost" value="0" />
			<property name="Type" value="Fate" />
			<property name="Force" value="1" />
			<property name="Combat Icons" value="UD:0, BD:0, T:0, EE-UD:0, EE-BD:0, EE-T:0" />
			<property name="Traits" value="" />
			<property name="Damage Capacity" value="0" />
			<property name="Resources" value="0" />
			<property name="Edge Priority" value="10" />
			<property name="Text" value="For this edge battle, this card gains +1 Force icon (to a maximum of +3) for each Endor objective or enhancement in play." />
			<property name="Flavor" value="" />
			<property name="Side" value="Dark" />
			<property name="Affiliation" value="Neutral" />
			<property name="Block" value="199" />
			<property name="Block Number" value="6" />
			<property name="Number" value="977" />
			<property name="Instructions" value="" />
			<property name="AutoScript" value="" />
			<property name="AutoAction" value="" />
		</card>
		<card id="ff4fb461-8060-457a-9c16-000000001255" name="Moon Blockade" size="ObjectiveSize">
			<property name="Cost" value="0" />
			<property name="Type" value="Objective" />
			<property name="Force" value="0" />
			<property name="Combat Icons" value="UD:0, BD:0, T:0, EE-UD:0, EE-BD:0, EE-T:0" />
			<property name="Traits" value="Endor" />
			<property name="Damage Capacity" value="5" />
			<property name="Resources" value="1" />
			<property name="Edge Priority" value="" />
			<property name="Text" value="Imperial Navy affiliation only.&#xD;&#xA;Each light side objective that has a copy in your victory pile is treated as if its printed text box were blank (except for Traits)." />
			<property name="Flavor" value="" />
			<property name="Side" value="Dark" />
			<property name="Affiliation" value="Imperial Navy" />
			<property name="Block" value="200" />
			<property name="Block Number" value="1" />
			<property name="Number" value="978" />
			<property name="Instructions" value="" />
			<property name="AutoScript" value="" />
			<property name="AutoAction" value="" />
		</card>
		<card id="ff4fb461-8060-457a-9c16-000000001256" name="Executor">
			<property name="Cost" value="6" />
			<property name="Type" value="Unit" />
			<property name="Force" value="3" />
			<property name="Combat Icons" value="UD:2, BD:2, T:0, EE-UD:1, EE-BD:1, EE-T:0" />
			<property name="Traits" value="Vehicle-Capital Ship-Death Squadron-Unique" />
			<property name="Damage Capacity" value="6" />
			<property name="Resources" value="0" />
			<property name="Edge Priority" value="" />
			<property name="Text" value="Elite.&#xD;&#xA;Reaction: After this unit enters play, deal 3 damage to a target objective." />
			<property name="Flavor" value="" />
			<property name="Side" value="Dark" />
			<property name="Affiliation" value="Imperial Navy" />
			<property name="Block" value="200" />
			<property name="Block Number" value="2" />
			<property name="Number" value="979" />
			<property name="Instructions" value="" />
			<property name="AutoScript" value="" />
			<property name="AutoAction" value="" />
		</card>
		<card id="ff4fb461-8060-457a-9c16-000000001257" name="Rear Admiral Chiraneau">
			<property name="Cost" value="3" />
			<property name="Type" value="Unit" />
			<property name="Force" value="2" />
			<property name="Combat Icons" value="UD:1, BD:0, T:0, EE-UD:1, EE-BD:1, EE-T:0" />
			<property name="Traits" value="Character-Officer-Unique" />
			<property name="Damage Capacity" value="2" />
			<property name="Resources" value="0" />
			<property name="Edge Priority" value="" />
			<property name="Text" value="Treat each enemy objective with 3 or more damage on it as if its printed text box were blank (except for Traits)." />
			<property name="Flavor" value="" />
			<property name="Side" value="Dark" />
			<property name="Affiliation" value="Imperial Navy" />
			<property name="Block" value="200" />
			<property name="Block Number" value="3" />
			<property name="Number" value="980" />
			<property name="Instructions" value="" />
			<property name="AutoScript" value="" />
			<property name="AutoAction" value="" />
		</card>
		<card id="ff4fb461-8060-457a-9c16-000000001258" name="Imperial Engineer">
			<property name="Cost" value="1" />
			<property name="Type" value="Unit" />
			<property name="Force" value="0" />
			<property name="Combat Icons" value="UD:0, BD:0, T:0, EE-UD:1, EE-BD:0, EE-T:0" />
			<property name="Traits" value="Character-Engineer" />
			<property name="Damage Capacity" value="1" />
			<property name="Resources" value="1" />
			<property name="Edge Priority" value="" />
			<property name="Text" value="Limited." />
			<property name="Flavor" value="" />
			<property name="Side" value="Dark" />
			<property name="Affiliation" value="Imperial Navy" />
			<property name="Block" value="200" />
			<property name="Block Number" value="4" />
			<property name="Number" value="981" />
			<property name="Instructions" value="" />
			<property name="AutoScript" value="" />
			<property name="AutoAction" value="" />
		</card>
		<card id="ff4fb461-8060-457a-9c16-000000001259" name="Jamming Protocol">
			<property name="Cost" value="1" />
			<property name="Type" value="Event" />
			<property name="Force" value="1" />
			<property name="Combat Icons" value="UD:0, BD:0, T:0, EE-UD:0, EE-BD:0, EE-T:0" />
			<property name="Traits" value="" />
			<property name="Damage Capacity" value="0" />
			<property name="Resources" value="0" />
			<property name="Edge Priority" value="" />
			<property name="Text" value="Interrupt: When an event card is played, cancel its effects." />
			<property name="Flavor" value="" />
			<property name="Side" value="Dark" />
			<property name="Affiliation" value="Imperial Navy" />
			<property name="Block" value="200" />
			<property name="Block Number" value="5" />
			<property name="Number" value="982" />
			<property name="Instructions" value="" />
			<property name="AutoScript" value="" />
			<property name="AutoAction" value="" />
		</card>
		<card id="ff4fb461-8060-457a-9c16-000000001260" name="Battle of Endor">
			<property name="Cost" value="0" />
			<property name="Type" value="Fate" />
			<property name="Force" value="1" />
			<property name="Combat Icons" value="UD:0, BD:0, T:0, EE-UD:0, EE-BD:0, EE-T:0" />
			<property name="Traits" value="" />
			<property name="Damage Capacity" value="0" />
			<property name="Resources" value="0" />
			<property name="Edge Priority" value="10" />
			<property name="Text" value="For this edge battle, this card gains +1 Force icon (to a maximum of +3) for each Endor objective or enhancement in play." />
			<property name="Flavor" value="" />
			<property name="Side" value="Dark" />
			<property name="Affiliation" value="Neutral" />
			<property name="Block" value="200" />
			<property name="Block Number" value="6" />
			<property name="Number" value="977" />
			<property name="Instructions" value="" />
			<property name="AutoScript" value="" />
			<property name="AutoAction" value="" />
		</card>
	</cards>
</set>
